pokerenv/__init__.py
pokerenv/common.py
pokerenv/obs_indices.py
pokerenv/player.py
pokerenv/table.py
pokerenv/utils.py
pokerenv-1.0.1.dist-info/LICENSE
pokerenv-1.0.1.dist-info/METADATA
pokerenv-1.0.1.dist-info/WHEEL
pokerenv-1.0.1.dist-info/top_level.txt
pokerenv-1.0.1.dist-info/RECORD
