Metadata-Version: 2.1
Name: pokerenv
Version: 1.0.1
Summary: A no limit hold'em environment for training RL agents.
Home-page: https://github.com/trouverun/pokerenv
Author: Trouverun
Author-email: aleksi.maki-penttila@tuni.fi
License: UNKNOWN
Platform: UNKNOWN
Classifier: Programming Language :: Python :: 3
Classifier: License :: OSI Approved :: MIT License
Classifier: Operating System :: OS Independent
Requires-Python: >=3.8
License-File: LICENSE
